{
    "ndcg_at_1": 0.19652,
    "ndcg_at_3": 0.24731,
    "ndcg_at_5": 0.26932,
    "ndcg_at_10": 0.29652,
    "ndcg_at_20": 0.32218,
    "ndcg_at_100": 0.3586,
    "ndcg_at_200": 0.36908,
    "ndcg_at_300": 0.3734,
    "ndcg_at_500": 0.38071,
    "ndcg_at_1000": 0.38654,
    "map_at_1": 0.15602,
    "map_at_3": 0.21506,
    "map_at_5": 0.23018,
    "map_at_10": 0.2423,
    "map_at_20": 0.24993,
    "map_at_100": 0.25563,
    "map_at_200": 0.25632,
    "map_at_300": 0.25649,
    "map_at_500": 0.25672,
    "map_at_1000": 0.25683,
    "recall_at_1": 0.15602,
    "recall_at_3": 0.28702,
    "recall_at_5": 0.34164,
    "recall_at_10": 0.42168,
    "recall_at_20": 0.51349,
    "recall_at_100": 0.6882,
    "recall_at_200": 0.75282,
    "recall_at_300": 0.78208,
    "recall_at_500": 0.83559,
    "recall_at_1000": 0.88372,
    "precision_at_1": 0.19652,
    "precision_at_3": 0.11982,
    "precision_at_5": 0.08781,
    "precision_at_10": 0.05522,
    "precision_at_20": 0.03464,
    "precision_at_100": 0.01004,
    "precision_at_200": 0.00563,
    "precision_at_300": 0.00394,
    "precision_at_500": 0.00259,
    "precision_at_1000": 0.00139,
    "mrr_at_1": 0.19652,
    "mrr_at_3": 0.26016,
    "mrr_at_5": 0.2726,
    "mrr_at_10": 0.28469,
    "mrr_at_20": 0.29178,
    "mrr_at_100": 0.2958,
    "mrr_at_200": 0.2962,
    "mrr_at_300": 0.29631,
    "mrr_at_500": 0.29641,
    "mrr_at_1000": 0.29647
}